{
  "hotels":[
	{"name":"Pestana Buenos Aires","starts":"5","price":"1000"},
	{"name":"Panamericano","starts":"5","price":"1000"},
	{"name":"Palermitano","starts":"5","price":"1000"},
	{"name":"Eco Pampa Palermo","starts":"5","price":"1000"},
	{"name":"Claridge Hotel","starts":"5","price":"1000"},
	{"name":"Unique Executive Central","starts":"5","price":"1000"},
	{"name":"Loi Suites Arenales","starts":"5","price":"1000"},
	{"name":"Sofitel La Reserva Cardales","starts":"5","price":"1000"},
	{"name":"Feir's Park","starts":"5","price":"1000"},
	{"name":"Reconquista Plaza	","starts":"5","price":"1000"},
	{"name":"Mayla","starts":"5","price":"1000"},
	{"name":"Emperador Buenos Aires	","starts":"5","price":"1000"},
	{"name":"Comfort Baires","starts":"5","price":"1000"},
	{"name":"Unique Palacio San Telmo","starts":"5","price":"1000"},
	{"name":"Napoleón","starts":"5","price":"1000"},
	{"name":"Babel Palermo","starts":"5","price":"1000"},
	{"name":"725 Continental","starts":"5","price":"1000"},
	{"name":"Pulitzer Buenos Aires","starts":"5","price":"1000"},
	{"name":"Hilton Buenos Aires","starts":"5","price":"1000"},
	{"name":"NH Collection Buenos Aires","starts":"5","price":"1000"},
	{"name":"Ilum","starts":"5","price":"1000"},
	{"name":"Globales Republica Wellnes","starts":"5","price":"1000"},
	{"name":"Regal Pacific Buenos Aires","starts":"5","price":"1000"},
	{"name":"Two","starts":"5","price":"1000"},
	{"name":"Byblos Palermo Soho","starts":"5","price":"1000"},
	{"name":"Argenta Suites Belgrano","starts":"5","price":"1000"},
	{"name":"Four Seasons Buenos Aires","starts":"5","price":"1000"},
	{"name":"Esplendor Buenos Aires","starts":"5","price":"1000"},
	{"name":"Bristol","starts":"5","price":"1000"},
	{"name":"NH Buenos Aires 9 de Julio	","starts":"5","price":"1000"},
	{"name":"Argenta Tower","starts":"5","price":"1000"},
	{"name":"Melia Buenos Aires","starts":"5","price":"1000"},
	{"name":"Bys Palermo","starts":"5","price":"1000"},
	{"name":"Apartaments Golf Tower	","starts":"5","price":"1000"},
	{"name":"HR Luxor Buenos Aires	","starts":"5","price":"1000"},
	{"name":"Etoile Recoleta","starts":"5","price":"1000"},
	{"name":"Callao Plaza Suites","starts":"5","price":"1000"},
	{"name":"Patios de San Telmo","starts":"5","price":"1000"},
	{"name":"Viamonte Buenos Aires Apart","starts":"5","price":"1000"},
	{"name":"Ayres de Recoleta Plaza","starts":"5","price":"1000"},
	{"name":"Apart Hotel & Spa Congreso","starts":"5","price":"1000"},
	{"name":"","starts":"5","price":"1000"}
	]
}
