{
	"hotels":[
	{
		"name":"Grand Hotel aaccf",
		"price":"4",
		"stars":"1022"
	},
	{
		"name":"Grand Hotel aalders",
		"price":"3",
		"stars":"855"
	},
	{
		"name":"Grand Hotel aaren",
		"price":"3",
		"stars":"1024"
	},
	{
		"name":"Grand Hotel aarika",
		"price":"3",
		"stars":"1050"
	},
	{
		"name":"Grand Hotel aaron",
		"price":"5",
		"stars":"1027"
	},
	{
		"name":"Grand Hotel aartjan",
		"price":"5",
		"stars":"923"
	},
	{
		"name":"Grand Hotel aasen",
		"price":"4",
		"stars":"1028"
	},
	{
		"name":"Grand Hotel ab",
		"price":"4",
		"stars":"928"
	},
	{
		"name":"Grand Hotel abacus",
		"price":"4",
		"stars":"1029"
	},
	{
		"name":"Grand Hotel abadines",
		"price":"5",
		"stars":"897"
	},
	{
		"name":"Grand Hotel abagael",
		"price":"3",
		"stars":"868"
	},
	{
		"name":"Grand Hotel abagail",
		"price":"5",
		"stars":"955"
	},
	{
		"name":"Grand Hotel abahri",
		"price":"5",
		"stars":"894"
	},
	{
		"name":"Grand Hotel abasolo",
		"price":"4",
		"stars":"973"
	},
	{
		"name":"Grand Hotel abazari",
		"price":"3",
		"stars":"875"
	},
	{
		"name":"Grand Hotel abba",
		"price":"3",
		"stars":"963"
	},
	{
		"name":"Grand Hotel abbai",
		"price":"5",
		"stars":"958"
	},
	{
		"name":"Grand Hotel abbas",
		"price":"4",
		"stars":"931"
	},
	{
		"name":"Grand Hotel abbatant",
		"price":"3",
		"stars":"901"
	},
	{
		"name":"Grand Hotel abbate",
		"price":"4",
		"stars":"1001"
	},
	{
		"name":"Grand Hotel abbe",
		"price":"3",
		"stars":"921"
	},
	{
		"name":"Grand Hotel abbey",
		"price":"5",
		"stars":"923"
	},
	{
		"name":"Grand Hotel abbi",
		"price":"3",
		"stars":"917"
	},
	{
		"name":"Grand Hotel abbie",
		"price":"5",
		"stars":"907"
	},
	{
		"name":"Grand Hotel abbot",
		"price":"3",
		"stars":"1009"
	},
	{
		"name":"Grand Hotel abbott",
		"price":"4",
		"stars":"932"
	},
	{
		"name":"Grand Hotel abby",
		"price":"4",
		"stars":"855"
	},
	{
		"name":"Grand Hotel abbye",
		"price":"4",
		"stars":"1014"
	},
	{
		"name":"Grand Hotel abdalla",
		"price":"5",
		"stars":"893"
	},
	{
		"name":"Grand Hotel abdallah",
		"price":"5",
		"stars":"854"
	},
	{
		"name":"Grand Hotel abdel",
		"price":"4",
		"stars":"1028"
	},
	{
		"name":"Grand Hotel abdel-az",
		"price":"3",
		"stars":"925"
	},
	{
		"name":"Grand Hotel abdel-ma",
		"price":"3",
		"stars":"1031"
	},
	{
		"name":"Grand Hotel abdel-ra",
		"price":"3",
		"stars":"952"
	},
	{
		"name":"Grand Hotel abdel-sa",
		"price":"5",
		"stars":"860"
	},
	{
		"name":"Grand Hotel abdelazi",
		"price":"4",
		"stars":"1002"
	},
	{
		"name":"Grand Hotel abdelmad",
		"price":"3",
		"stars":"1006"
	},
	{
		"name":"Grand Hotel abdelrah",
		"price":"4",
		"stars":"1023"
	},
	{
		"name":"Grand Hotel abdelran",
		"price":"5",
		"stars":"937"
	},
	{
		"name":"Grand Hotel abdelsal",
		"price":"4",
		"stars":"1024"
	},
	{
		"name":"Grand Hotel abderrao",
		"price":"5",
		"stars":"873"
	},
	{
		"name":"Grand Hotel abderraz",
		"price":"4",
		"stars":"862"
	},
	{
		"name":"Grand Hotel abdi",
		"price":"3",
		"stars":"867"
	},
	{
		"name":"Grand Hotel abdo",
		"price":"3",
		"stars":"1041"
	},
	{
		"name":"Grand Hotel abdollah",
		"price":"4",
		"stars":"1000"
	},
	{
		"name":"Grand Hotel abdolrah",
		"price":"3",
		"stars":"993"
	},
	{
		"name":"Grand Hotel abdou",
		"price":"5",
		"stars":"946"
	},
	{
		"name":"Grand Hotel abdrani",
		"price":"4",
		"stars":"871"
	},
	{
		"name":"Grand Hotel abdul",
		"price":"3",
		"stars":"1044"
	},
	{
		"name":"Grand Hotel abdul-az",
		"price":"4",
		"stars":"884"
	},
	{
		"name":"Grand Hotel abdul-ma",
		"price":"3",
		"stars":"932"
	},
	{
		"name":"Grand Hotel abdul-no",
		"price":"4",
		"stars":"877"
	},
	{
		"name":"Grand Hotel abdul-ra",
		"price":"3",
		"stars":"1039"
	},
	{
		"name":"Grand Hotel abdul-sa",
		"price":"3",
		"stars":"975"
	},
	{
		"name":"Grand Hotel abdulazi",
		"price":"5",
		"stars":"1032"
	},
	{
		"name":"Grand Hotel abdulla",
		"price":"3",
		"stars":"875"
	},
	{
		"name":"Grand Hotel abdullah",
		"price":"5",
		"stars":"967"
	},
	{
		"name":"Grand Hotel abdulmad",
		"price":"4",
		"stars":"1010"
	},
	{
		"name":"Grand Hotel abdulrah",
		"price":"4",
		"stars":"908"
	},
	{
		"name":"Grand Hotel abdulran",
		"price":"3",
		"stars":"856"
	},
	{
		"name":"Grand Hotel abdulsal",
		"price":"4",
		"stars":"990"
	}
  ]
}
